[
    {
        "label": "Electric current",
        "value": "13ab2e82-04d0-481e-b470-651a6742e089"
    },
    {
        "label": "Pipeline Transport",
        "value": "28f21a4f-859b-410d-9da4-6f8385a60815"
    },
    {
        "label": "Freight transportation",
        "value": "1c83b082-72ba-423d-b0b7-ef11896936c9"
    },
    {
        "label": "Office machines and automatic data-processing machines",
        "value": "43f1fc4d-256e-4e2d-83ae-4c63a2321fd8"
    },
    {
        "label": "Non-metallic mineral manufactures, n.e.s.",
        "value": "89c604ca-24a7-440b-b93d-5f5bba151e8b"
    },
    {
        "label": "Guarantees and commitments",
        "value": "c5215eec-90d8-4602-8e89-4e5cee731295"
    },
    {
        "label": "Road Transport Services",
        "value": "ee1959e3-391e-45a6-a1b4-b9e000de2cae"
    },
    {
        "label": "Machinery and transport equipment",
        "value": "724fa0de-e1f3-4597-968e-eddd6688a548"
    },
    {
        "label": "Sewage services",
        "value": "a2e4f4e1-8f0c-4064-89b2-75cc5ba8b763"
    },
    {
        "label": "Fertilizers (other than those of group 272)",
        "value": "e2f8e9bd-7858-49ed-8bfe-116772e235c0"
    },
    {
        "label": "Others",
        "value": "cf0fee53-5d22-4adc-9da7-6023eeb210b2"
    },
    {
        "label": "Acceptance of deposits and other repayable funds from the public",
        "value": "9e70a234-4238-48e7-915f-c4bd58d8d53a"
    },
    {
        "label": "Real Estate Services",
        "value": "a45375c4-54cc-4d04-bc96-b7557304862a"
    },
    {
        "label": "OTHER SERVICES NOT INCLUDED ELSEWHERE",
        "value": "06419fe3-878b-4147-8031-f4537149f19c"
    },
    {
        "label": "Servicios de carga y descarga",
        "value": "8f47f300-5c24-4fa6-be35-1a475fe643fb"
    },
    {
        "label": "Iron and steel",
        "value": "20aff6ee-de8c-43ce-913d-23145f3222f4"
    },
    {
        "label": "Veterinary services",
        "value": "d15df049-c0b4-4a76-8960-54e51092597f"
    },
    {
        "label": "Primary education services",
        "value": "0279ef07-c3ce-4ec5-a31a-ceccb85ba51b"
    },
    {
        "label": "RECREATIONAL, CULTURAL AND SPORTING SERVICES
(other than audiovisual services)",
        "value": "9fa4fea8-6c8f-40e8-9ece-57aea5e1e71a"
    },
    {
        "label": "Other",
        "value": "88b3456b-23d9-430d-bf88-11f933dc119a"
    },
    {
        "label": "Related scientific and technical consulting services",
        "value": "0b0dd734-aa25-4ad2-8d7e-afd53279396b"
    },
    {
        "label": "Feeding stuff for animals (not including unmilled cereals)",
        "value": "a6ee4d25-8f19-494c-908d-2eba133820ad"
    },
    {
        "label": "Animal and vegetable oils, fats and waxes",
        "value": "54db828e-c35c-41e0-a186-732b3eac4526"
    },
    {
        "label": "Leather, leather manufactures, n.e.s., and dressed furskins",
        "value": "126ae1f3-932d-42ee-9ec4-44df17ef1189"
    },
    {
        "label": "Passenger transportation",
        "value": "6fa4f3e8-7331-467a-aa80-27f3fbd33d08"
    },
    {
        "label": "Maintenance and repair of aircraft",
        "value": "9cf7cd24-eb4e-473d-9559-3d00aa1b76c0"
    },
    {
        "label": "Other",
        "value": "5f114b67-b7d7-4507-a59f-de9c7fce6272"
    },
    {
        "label": "Passenger transportation",
        "value": "cad5309f-1d5b-40ae-9fcb-2bb43a9d3062"
    },
    {
        "label": "Essential oils and resinoids and perfume materials; toilet, polishing and cleansing preparations",
        "value": "c8730a2d-ac99-41f3-8ba8-c463c359b098"
    },
    {
        "label": "Refuse disposal services",
        "value": "10d1895c-96c0-4222-aa64-b705dec01031"
    },
    {
        "label": "TOURISM AND TRAVEL RELATED SERVICES",
        "value": "2c026ad7-1eb3-4be0-8c0b-d09c80903950"
    },
    {
        "label": "Hides, skins and furskins, raw",
        "value": "c6259cde-f9cd-4bf4-b810-a7fdcbe5da50"
    },
    {
        "label": "Rental of aircraft with crew",
        "value": "973e3f00-f1f8-44a1-bbf3-72dc03c4c73d"
    },
    {
        "label": "Rental of vessels with crew",
        "value": "f70dd4a7-49d9-41c5-99b5-7cbab442a85a"
    },
    {
        "label": "Services auxiliary to all modes of transport       ",
        "value": "dc0ecec7-397c-4b1c-97b1-45883c9bec0a"
    },
    {
        "label": "Primary education services",
        "value": "19ab86b6-d688-4b49-b280-c64513c7d91d"
    },
    {
        "label": "Paper, paperboard and articles of paper pulp, of paper or of paperboard",
        "value": "3f2f9fdd-b935-40e1-a947-da1be02ee98d"
    },
    {
        "label": "Special transactions and commodities not classified according to kind",
        "value": "8f933f83-263a-4ded-93de-647f56bb65b9"
    },
    {
        "label": "Textile yarn, fabrics, made-up articles, n.e.s., and related products",
        "value": "a9205727-b4f1-4682-9911-3ca9449c9e09"
    },
    {
        "label": "Beverages and tobacco",
        "value": "663ae2bf-fc55-4064-a1e2-db0af580b635"
    },
    {
        "label": "Others",
        "value": "c1baa26e-50de-4074-aa01-2881a1b4234a"
    },
    {
        "label": "Travel goods, handbags and similar containers",
        "value": "61a0f895-1986-42f1-bb17-d87e5502f224"
    },
    {
        "label": "Data base services",
        "value": "08324325-7b43-4dd5-a4a7-aad5cd3714ee"
    },
    {
        "label": "Banking and other financial services (excl. insurance)",
        "value": "b5d69e19-00e5-4aa5-8f7b-84a1266df81f"
    },
    {
        "label": "Tobacco and tobacco manufactures",
        "value": "2ee2c112-e8be-44fe-b0d8-13169edcf2f4"
    },
    {
        "label": "General construction work for buildings ",
        "value": "fb15f79a-0b0f-4d5d-8686-4d080a8baf13"
    },
    {
        "label": "Investigation and security",
        "value": "22eafe52-6909-42a6-9e65-cf57723569be"
    },
    {
        "label": "Urban planning and landscape architectural services       ",
        "value": "085c58cc-9d45-41ab-96c9-46327e54ef4c"
    },
    {
        "label": "Commission agents' services",
        "value": "262497c5-438d-4fd3-a009-e0eeff9563cf"
    },
    {
        "label": "FINANCIAL SERVICES",
        "value": "3db025f5-434d-46a2-88e9-16aed5ee0ccc"
    },
    {
        "label": "Motion picture projection service",
        "value": "589ed6eb-9016-4e7c-8607-2456d4f82e2c"
    },
    {
        "label": "Food and live animals",
        "value": "cc357bb6-86d8-437b-b8a8-4e239418b8d2"
    },
    {
        "label": "Retailing services",
        "value": "d4cecffc-aa2f-4268-82bd-85a840b3f1fe"
    },
    {
        "label": "Fixed vegetable fats and oils, crude, refined or fractionated",
        "value": "a1e0a1e6-013c-43dd-b707-2a4e4d0b852e"
    },
    {
        "label": "Live animals other than animals of division 03",
        "value": "93201d7b-686f-452d-9854-441ed3b04444"
    },
    {
        "label": "Installation and assembly work",
        "value": "863661ce-777a-4ec3-a7c0-3ac1378fb429"
    },
    {
        "label": "Travel agencies and tour operators services",
        "value": "493e43bf-1f1c-4b2b-88cd-7da69741e77c"
    },
    {
        "label": "Transportation of fuels",
        "value": "06443c49-b62e-4bd7-8ed5-1174ed0b153e"
    },
    {
        "label": "Services incidental to agriculture, hunting and forestry",
        "value": "c31d7248-ef6d-4094-a4e5-db209f5ad0bd"
    },
    {
        "label": "Rental of commercial vehicles with operator",
        "value": "b146aad6-bf79-453a-a259-391e4e850b54"
    },
    {
        "label": "Franchising",
        "value": "86fd3722-3b1d-4b10-9b38-67bf56b4632b"
    },
    {
        "label": "Animal or vegetable fats and oils, processed; waxes of animal or vegetable origin; inedible mixtures or preparations of animal or vegetable fats or oils, n.e.s.",
        "value": "5f13d462-d292-4340-9295-1673e0c2b781"
    },
    {
        "label": "Relating to ships",
        "value": "8b3bd2c9-61c9-4c99-a278-b65b41283ae9"
    },
    {
        "label": "Participation in issues of all kinds of securities, incl. under-writing and placement as agent (whether publicly or privately) and provision of service related to such issues",
        "value": "20786439-54d5-46e6-86a6-34dfb5406e66"
    },
    {
        "label": "Other",
        "value": "4c573739-3263-4552-8526-7acad8647124"
    },
    {
        "label": "Pushing and towing services",
        "value": "8a6f4633-d011-4e25-bd6c-a60be1ea769c"
    },
    {
        "label": "Building-cleaning services",
        "value": "96c3d6af-db6a-4215-988c-fbcb332e845c"
    },
    {
        "label": "On a fee or contract basis",
        "value": "9f8c00da-fa76-412e-af8f-f56a53f373f2"
    },
    {
        "label": "Computer and Related Services",
        "value": "4ffd315b-de21-4072-87d1-60e345cdb689"
    },
    {
        "label": "Asset management, such as cash or portfolio management, all forms of collective investment management, pension fund management, custodial depository and trust services       ",
        "value": "bc48e0cc-5e30-424e-9be7-dfa6dbef96a6"
    },
    {
        "label": "Voice telephone services",
        "value": "7cf28436-2479-4330-874a-60d684657b68"
    },
    {
        "label": "General construction work for buildings ",
        "value": "76ed1b19-df40-4ff4-8293-114d75a2bcaa"
    },
    {
        "label": "News agency services",
        "value": "bfff3618-6a21-4bf9-b112-8f99aec48eff"
    },
    {
        "label": "Other",
        "value": "a4556edb-1d7d-4bc4-80e3-b637ff4c8e3e"
    },
    {
        "label": "SR&D services on natural sciences",
        "value": "df68a78d-7456-47c3-8ec2-4fed6cc6816b"
    },
    {
        "label": "Legal Services",
        "value": "68d88072-02fc-43db-87c0-5b84cb553858"
    },
    {
        "label": "Chemicals and related products, n.e.s.",
        "value": "83ba4a90-18ee-4a63-bed4-5cea6afc7bd6"
    },
    {
        "label": "Maintenance and repair of vessels",
        "value": "1d0f3437-40da-47d7-9a78-e37c5b9b723c"
    },
    {
        "label": "Other education services",
        "value": "1d5f9668-d1f5-414c-aa13-b04036a7b13f"
    },
    {
        "label": "Other",
        "value": "b5771959-afa1-4260-abd1-7303610f797f"
    },
    {
        "label": "Others",
        "value": "5111b3ba-b73f-4abc-81ec-ccc6c5e16be8"
    },
    {
        "label": "CONSTRUCTION AND RELATED ENGINEERING SERVICES ",
        "value": "607a726d-6c1d-4108-a7fb-304328adbb28"
    },
    {
        "label": "Adult education",
        "value": "3e3934a6-10e5-4b51-a68c-444e8a877dc4"
    },
    {
        "label": "Pulp and waste paper",
        "value": "83f48ef5-c5e8-4813-ba8f-ecf10e481357"
    },
    {
        "label": "Social Services",
        "value": "3addadfd-5358-4176-bfdc-7561e34f2ab5"
    },
    {
        "label": "Postal services",
        "value": "5f82e552-e4c7-4d13-bb7e-2d375c566fdb"
    },
    {
        "label": "TRANSPORT SERVICES",
        "value": "7f21856c-6ff6-4ffa-9796-0082549bd11f"
    },
    {
        "label": "Packet-switched data transmission services",
        "value": "6c7451cc-de0d-4f74-be61-3de6cab30af8"
    },
    {
        "label": "Road vehicles (including air-cushion vehicles)",
        "value": "2d6652bf-f440-41b6-a7a2-1020c2c50834"
    },
    {
        "label": "Enhanced/value-added facsimile services, incl. store and forward, store and retrieve",
        "value": "8c84310f-8496-4e23-a930-7b8bf65b7177"
    },
    {
        "label": "Professional Services",
        "value": "a59a3b9f-53ad-4fe5-acd2-53fc6f1c850a"
    },
    {
        "label": "Refuse disposal services",
        "value": "439b80f0-4dc7-44b8-a50f-44823721f06b"
    },
    {
        "label": "Freight transportation",
        "value": "5bc034ac-342c-414b-8394-18cf41c476ab"
    },
    {
        "label": "Interdisciplinary R&D services",
        "value": "a6497fa4-2efa-4973-a45d-09526ecb9f25"
    },
    {
        "label": "Rail Transport Services",
        "value": "6c27af39-edb1-4207-9bf3-5e240ab71689"
    },
    {
        "label": "Dyeing, tanning and colouring materials",
        "value": "78cfb731-52fc-4f9a-a7b4-ea02043a7a65"
    },
    {
        "label": "Others",
        "value": "64739b24-c1c3-498d-bb57-54d03aa32448"
    },
    {
        "label": "Sound recording",
        "value": "6e28fd05-4cbc-4281-8dbe-422af52f1106"
    },
    {
        "label": "Social Services",
        "value": "f701fac4-6f12-4f1e-8a39-899ca3ec91b0"
    },
    {
        "label": "Petroleum, petroleum products and related materials",
        "value": "4540795e-3705-4f40-9ef8-a136adf50a04"
    },
    {
        "label": "Mineral fuels, lubricants and related materials",
        "value": "0657d265-fab1-4e94-94ed-af6d88933f94"
    },
    {
        "label": "ENVIRONMENTAL SERVICES",
        "value": "5bdc38de-2f19-40b6-a4de-f228163cc6a6"
    },
    {
        "label": "Footwear",
        "value": "7d84975a-5d94-44a8-9e4f-9340ee2f76e0"
    },
    {
        "label": "General industrial machinery and equipment, n.e.s., and machine parts, n.e.s.",
        "value": "1cb1ef1d-2b3f-4e58-b751-9d67b3e828eb"
    },
    {
        "label": "Photographic apparatus, equipment and supplies and optical goods, n.e.s.; watches and clocks",
        "value": "6f4110d9-cbac-442b-b5de-abeb6809bb2b"
    },
    {
        "label": "Hospital services",
        "value": "f5d1371e-2088-4aab-908b-81ec1ccb39ae"
    },
    {
        "label": "On-line information and data base retrieval",
        "value": "f6918e07-8e19-499a-a8f2-59bf305d0a17"
    },
    {
        "label": "Other",
        "value": "ec30c85b-01b6-47fb-9e9c-911e4ab67886"
    },
    {
        "label": "Services incidental to energy distribution",
        "value": "8aea549e-4caf-4388-ad6c-f6b4d58fd505"
    },
    {
        "label": "Facsimile services",
        "value": "d2bfe097-e327-46f3-8bdb-6472f4670811"
    },
    {
        "label": "Servicios de agencias de transporte de carga",
        "value": "93b06891-fed6-42d9-ab71-9dbd1368fbd4"
    },
    {
        "label": "Private leased circuit services",
        "value": "6c46907d-c69c-447d-b511-60fd579bcba0"
    },
    {
        "label": "Coal, coke and briquettes",
        "value": "238929d7-5a32-483a-ad39-7611c3a879eb"
    },
    {
        "label": "Medicinal and pharmaceutical products",
        "value": "d1cc4143-6e19-412b-b705-aab7c3a5ab85"
    },
    {
        "label": "Voice mail",
        "value": "891dc8cf-7282-4cb9-a3cf-5757e4d82d0e"
    },
    {
        "label": "Maintenance and repair of rail transport equipment",
        "value": "43a0aba8-f582-4870-93b7-fe8b889b30f3"
    },
    {
        "label": "Maintenance and repair of vessels",
        "value": "3adfda23-78b6-4e23-b719-43a4e8beb21c"
    },
    {
        "label": "Manufactures of metals, n.e.s.",
        "value": "513743dd-9ade-46a0-8c06-edc836671c6e"
    },
    {
        "label": "DISTRIBUTION SERVICES    ",
        "value": "f4e7d90b-bf7d-4abb-8757-9802f4c772d7"
    },
    {
        "label": "All insurance and insurance-related services",
        "value": "cc32b622-dd2e-461e-b7a2-7ca966e18222"
    },
    {
        "label": "Management consulting service",
        "value": "f21af7be-cd15-499e-b8d5-d1092cb00081"
    },
    {
        "label": "Articles of apparel and clothing accessories",
        "value": "b55d80eb-92ac-425d-8957-73f53082cc28"
    },
    {
        "label": "Non-life insurance services",
        "value": "2e77bbb6-924c-496e-ae61-6acad134b646"
    },
    {
        "label": "Franchising",
        "value": "1d3cd53d-3b52-4c75-bf6b-7ebef01c848c"
    },
    {
        "label": "Others",
        "value": "ba0494a1-15d6-471a-9fbe-6af5093d5d80"
    },
    {
        "label": "Other Human Health Services",
        "value": "d1b5ca07-8cad-4b2c-823d-f628e6b1dd90"
    },
    {
        "label": "Rental of vessels with crew",
        "value": "f647bc06-e286-48f3-9fcc-ca72d4b03dcb"
    },
    {
        "label": "Coffee, tea, cocoa, spices, and manufactures thereof",
        "value": "d2694f12-97e2-4fd9-9187-f45a3f59a5c6"
    },
    {
        "label": "Architectural services",
        "value": "4a3c6fda-b026-4a4b-84a3-a331dcd624e7"
    },
    {
        "label": "Higher education services",
        "value": "8291e233-b3eb-46a8-8ec6-06034aa526a0"
    },
    {
        "label": "Libraries, archives, museums and other cultural services",
        "value": "05c809c4-5740-4e47-9b5c-5cc6c049fef3"
    },
    {
        "label": "Cork and wood manufactures (excluding furniture)",
        "value": "94252a25-4bd1-44ef-af20-79780890b37c"
    },
    {
        "label": "All payment and money transmission services",
        "value": "f3306814-81ac-4083-bbca-08307c396ba9"
    },
    {
        "label": "Other",
        "value": "4e8ab57b-9b47-4bde-ac29-9c73280c7d9a"
    },
    {
        "label": "Vegetables and fruit",
        "value": "703953f5-d1ef-4cfb-a377-42282a87a49c"
    },
    {
        "label": "Professional, scientific and controlling instruments and apparatus, n.e.s.",
        "value": "fb3c0a42-b5a7-498a-9730-0de7651dd0d4"
    },
    {
        "label": "Secondary education services",
        "value": "c8a7f367-32d1-4699-93b2-2b3484e4b1f1"
    },
    {
        "label": "Electrical machinery, apparatus and appliances, n.e.s., and electrical parts thereof (including non-electrical counterparts, n.e.s., of electrical household-type equipment)",
        "value": "262a7aa9-8305-4312-91e6-1cb0e62d91f6"
    },
    {
        "label": "Maritime Transport Services       ",
        "value": "eb4895c5-dedc-473a-8f59-131715d88507"
    },
    {
        "label": "Research and Development Services",
        "value": "7b13c47a-fe7d-4c1e-8e71-da5cc21f7fcd"
    },
    {
        "label": "Code and protocol conversion",
        "value": "33c9fa0f-e029-40b5-afa4-fb123dede915"
    },
    {
        "label": "Life, accident and health insurance services",
        "value": "595a9576-7c26-4ca8-8487-64d8d9cb05c2"
    },
    {
        "label": "Sewage services",
        "value": "20211f04-c98b-4c3a-9cf8-cbc569ee2b40"
    },
    {
        "label": "Advertising services",
        "value": "1dba80e6-9093-456f-8ed7-e15df19221fb"
    },
    {
        "label": "Rubber manufactures, n.e.s.",
        "value": "6d013c63-9c5f-4458-b560-be106d20e15f"
    },
    {
        "label": "Crude fertilizers, other than those of division 56, and crude minerals (excluding coal, petroleum and precious stones)",
        "value": "31cf82a7-149f-476c-92b0-eae5e8ca501f"
    },
    {
        "label": "Passenger transportation",
        "value": "0e6a58d5-ee04-4d71-814e-511ff35cee87"
    },
    {
        "label": "Passenger transportation",
        "value": "7bdc83d3-5118-49ab-b949-af6c3e2ec695"
    },
    {
        "label": "asasa",
        "value": "a2c9f7fe-1a84-43bd-bd23-a8c22d0b930d"
    },
    {
        "label": "Involving own or leased property",
        "value": "154aede1-36ea-4e1c-9a16-537f70186cbd"
    },
    {
        "label": "Installation and assembly work",
        "value": "075fbee9-ba11-4158-820c-485d894e1490"
    },
    {
        "label": "Other Business Services",
        "value": "fa5d876f-b1e7-4894-b9c9-e85dff80981a"
    },
    {
        "label": "Miscellaneous edible products and preparations",
        "value": "4d835010-7513-481a-9739-076016495e4a"
    },
    {
        "label": "Money broking",
        "value": "682d09c0-45f0-4eb9-80d9-34dbbc5903a4"
    },
    {
        "label": "Dairy products and birds' eggs",
        "value": "4e869a4e-ec69-4624-a1ce-11c2b7927067"
    },
    {
        "label": "COMMUNICATION SERVICES",
        "value": "93a5a24d-bb1f-4dbc-ae3a-beed2ca13dbb"
    },
    {
        "label": "Maintenance and repair of equipment (not including maritime vessels, aircraftor or other transport equipment)             ",
        "value": "6d840bf3-5cf2-4d8a-aa64-8f9db43b7306"
    },
    {
        "label": "Other",
        "value": "1760dd12-24e0-4fad-9a26-4ec3b6d10a7b"
    },
    {
        "label": "Maintenance and repair of road transport equipment ",
        "value": "6c02291c-1939-47bb-b72c-aa1de4edf419"
    },
    {
        "label": "Freight transportation",
        "value": "9639ce99-ddf8-447b-910f-a68d65d2b884"
    },
    {
        "label": "Commodities and transactions not classified elsewhere in the SITC",
        "value": "b1f6272e-5672-481d-8d06-c531569da45c"
    },
    {
        "label": "Sporting and other recreational services",
        "value": "7e1e8cb6-b7e3-461a-ac3a-74bd94744a3f"
    },
    {
        "label": "Other",
        "value": "81e720a8-2be4-4183-aca4-4972a85f0299"
    },
    {
        "label": "Adult education",
        "value": "2714de0a-312c-48d4-ae8a-2dd2841b464d"
    },
    {
        "label": "Integrated engineering services",
        "value": "35eb3c8a-56bc-4923-9194-457b7ce4c36e"
    },
    {
        "label": "SSanitation and similar services",
        "value": "086469e1-0de1-4c50-859c-c13add56ee83"
    },
    {
        "label": "Services incidental to mining",
        "value": "fcc613da-b824-4e2e-81de-dd6a292e5c03"
    },
    {
        "label": "Reinsurance and retrocession",
        "value": "5319f4cc-23d9-44be-bf1a-944470dfd85e"
    },
    {
        "label": "Courier services",
        "value": "c9a3b7a8-e8d6-4e2d-b08d-d7231572d95e"
    },
    {
        "label": "Space Transport",
        "value": "37369620-f0be-4010-ae36-1ddb6d17aa93"
    },
    {
        "label": "Supporting services for rail transport services",
        "value": "5a6fc026-8f54-48b1-b8e0-73389526361e"
    },
    {
        "label": "Telex services",
        "value": "094fe8a0-c0d5-4b0c-aa28-5399f34887e5"
    },
    {
        "label": "Power-generating machinery and equipment",
        "value": "b4b401b7-7169-4783-b990-1c974284bc69"
    },
    {
        "label": "Cork and wood",
        "value": "2403af10-fa09-4ba6-9d19-4b6bc0dfab33"
    },
    {
        "label": "Cereals and cereal preparations",
        "value": "e4d7cdb0-6692-47a1-8ca6-a6d787e4e12d"
    },
    {
        "label": "Medical and dental services",
        "value": "139dcfe0-4cf4-4f28-b627-3ceaae4db948"
    },
    {
        "label": "EDUCATIONAL SERVICES                                          ",
        "value": "34f1f47e-53e5-4dec-bb27-cb36e5b8ad0f"
    },
    {
        "label": "Courier services",
        "value": "7cc3e3ac-9399-4ad6-857e-92c5fa9bf6ea"
    },
    {
        "label": "Others",
        "value": "bd52c3a0-b913-415f-8514-f4deb4e84ab2"
    },
    {
        "label": "Other",
        "value": "012ce589-d7fd-453f-88b6-44faa9662fd7"
    },
    {
        "label": "Radio and television transmission services",
        "value": "6473ccf6-f8d1-4fcd-87fd-0ba685f6ffc0"
    },
    {
        "label": "Services incidental to fishing",
        "value": "fa7f409b-08a3-4e01-8e54-f68e56f3d025"
    },
    {
        "label": "Supporting services for road transport services",
        "value": "c0939862-5ea6-40c7-bba1-63a9a0f4d54a"
    },
    {
        "label": "Other education services",
        "value": "3c22de90-876b-47da-ae2c-2a6d3d51944f"
    },
    {
        "label": "News agency services",
        "value": "106114ca-ec2c-41ef-947a-dc6b5d7449d5"
    },
    {
        "label": "Radio and television services",
        "value": "e38615c7-845c-4564-8ba3-6f1151f9b36c"
    },
    {
        "label": "Secondary education services",
        "value": "e6f856bc-f5bd-4a88-888b-dd657c391ab5"
    },
    {
        "label": "Financial leasing",
        "value": "20e45939-07ae-4e0e-8c0a-47a6461793bd"
    },
    {
        "label": "General construction work for civil engineering ",
        "value": "692af027-dcec-4877-b717-66ebb027b976"
    },
    {
        "label": "Lending of all types, incl., inter alia, consumer credit, mortgage credit, factoring and financing of commercial transaction ",
        "value": "8dc7f9a0-01a6-4285-a0af-2120eda1e693"
    },
    {
        "label": "Other transport equipment",
        "value": "25c2c881-ad52-4822-8868-60f8ccaa9a1a"
    },
    {
        "label": "Others ",
        "value": "74707815-ac43-4a82-87b1-d3ac5d6824fd"
    },
    {
        "label": "Telecommunication services",
        "value": "b175ddc5-c657-4de6-90c7-de36e7c6bd14"
    },
    {
        "label": "Textile fibres (other than wool tops and other combed wool) and their wastes (not manufactured into yarn or fabric)",
        "value": "6a339fcc-f819-4056-8f05-9e3473191e06"
    },
    {
        "label": "Higher education services",
        "value": "90da5e6d-95be-423c-93de-68849c2587f3"
    },
    {
        "label": "Sugars, sugar preparations and honey",
        "value": "1a4188d3-ca4e-468a-9077-69ab2b7b25de"
    },
    {
        "label": "Telecommunications and sound-recording and reproducing apparatus and equipment",
        "value": "4edf0b60-ced4-4ffc-a68b-2c8b7a48982a"
    },
    {
        "label": "Rental/Leasing Services without Operators",
        "value": "84884ca3-431d-4941-adbf-65cf6567e318"
    },
    {
        "label": "Pushing and towing services",
        "value": "19e7ddff-e4ad-4268-b844-8e48683e4f94"
    },
    {
        "label": "Furniture, and parts thereof; bedding, mattresses, mattress supports, cushions and similar stuffed furnishings",
        "value": "224d3c5a-7c53-48cb-8aab-8677e1f6ae06"
    },
    {
        "label": "Tourist guides services",
        "value": "f5690f15-7639-4398-bbd3-f30bc83d5038"
    },
    {
        "label": "Wholesale trade services",
        "value": "672905de-a4ae-4390-9893-ba93d507232d"
    },
    {
        "label": "Supporting services for air transports",
        "value": "00aec3d1-c2f2-4d70-aa45-64fe6694d197"
    },
    {
        "label": "SSanitation and similar services",
        "value": "bc136c4f-6cc9-423b-95a5-3297a917b1b8"
    },
    {
        "label": "Libraries, archives, museums and other cultural services",
        "value": "7fa3b70b-f3fb-490c-88fb-196a4eb70b2a"
    },
    {
        "label": "Commission agents' services",
        "value": "56791027-1f00-4fc0-9409-557526a887f1"
    },
    {
        "label": "Building completion and finishing work",
        "value": "2360d64f-fe30-4293-9888-e8748da2909f"
    },
    {
        "label": "Engineering services",
        "value": "1051930b-4716-4df4-a7fe-9fdd93ba2d40"
    },
    {
        "label": "Market research and public opinion polling services",
        "value": "519a63f7-ae54-4014-b115-5d85b9432fc0"
    },
    {
        "label": "Freight transportation",
        "value": "79b68f33-2940-4415-9d9f-92daf833db8d"
    },
    {
        "label": "Relating to other transport equipment ",
        "value": "02606a49-dcac-457d-8a5b-de41eded251c"
    },
    {
        "label": "Placement and supply services of Personnel",
        "value": "445e4401-4f15-48ee-b012-3e596d61f962"
    },
    {
        "label": "Prefabricated buildings; sanitary, plumbing, heating and lighting fixtures and fittings, n.e.s.",
        "value": "f8a662b2-01de-4a9c-96f4-2bf60da2e218"
    },
    {
        "label": "Photographic services",
        "value": "533573f7-7bb8-46b5-bd1f-7b2fd3dd50c9"
    },
    {
        "label": "Internal Waterways Transport       ",
        "value": "7f4406cc-835b-4b3c-9ed1-86bec36c3e68"
    },
    {
        "label": "Postal packages not classified according to kind",
        "value": "d37bef45-5c68-47f9-bfd9-c47b0b1d32c0"
    },
    {
        "label": "Services provided by midwives, nurses,physiotherapists and para-medical personnel",
        "value": "ecae4a61-92d1-4c1b-8d72-98acb1fc9d44"
    },
    {
        "label": "Other Transport Services ",
        "value": "a37fb0af-8199-4bba-bff0-4133746a36bb"
    },
    {
        "label": "Miscellaneous manufactured articles",
        "value": "67d0edf0-e9a0-4db1-b372-88e0d8edb0d2"
    },
    {
        "label": "Metalliferous ores and metal scrap",
        "value": "bda93d6d-8715-4c5b-ad15-81cab5d87505"
    },
    {
        "label": "On-line information and/or data processing (incl.transaction processing)",
        "value": "790a90c2-7559-42d1-8c3c-8d5d7fd7f393"
    },
    {
        "label": "Services related to man. consulting ",
        "value": "c2f9f020-ae85-4f8d-8a90-d4b10ad1066c"
    },
    {
        "label": "Others",
        "value": "bf1c663c-09ed-411c-a4ce-1c39606cb151"
    },
    {
        "label": "Animal oils and fats",
        "value": "831fe888-5e70-4d2f-8cd1-37d68b6ab8cf"
    },
    {
        "label": "Other",
        "value": "e2279c8c-029a-45d9-a8de-e447738847d1"
    },
    {
        "label": "Non-ferrous metals",
        "value": "180a500c-4cdf-4c04-934d-c556704018a7"
    },
    {
        "label": "Pushing and towing services",
        "value": "c7190c0f-8b24-4964-9731-49329b8a3a88"
    },
    {
        "label": "Services incidental to manufacturing",
        "value": "fbc6562c-9576-415d-a0a3-e5fbe6788545"
    },
    {
        "label": "Travel agencies and tour operators services",
        "value": "e00d00d3-dc5c-4df5-ae01-5df434ec590e"
    },
    {
        "label": "Wholesale trade services",
        "value": "9d61a671-0ec7-434b-8027-7d7f72d04c9b"
    },
    {
        "label": "Software implementation services",
        "value": "4d008930-e0cf-4960-a336-66a2c12c959f"
    },
    {
        "label": "General construction work for civil engineering ",
        "value": "93b501bc-71dc-46b3-ab6d-d067db277282"
    },
    {
        "label": "Transportation of other goods",
        "value": "0153c4a2-e21f-49bc-ad34-118846fffc2e"
    },
    {
        "label": "Hospital services",
        "value": "e08c8c9f-5cb7-49c4-ad66-8c7531829552"
    },
    {
        "label": "Others",
        "value": "fcea46d8-de5d-498f-af06-834be9681732"
    },
    {
        "label": "Retailing services",
        "value": "2596fe17-8a7c-48e1-861d-e1cace316074"
    },
    {
        "label": "Relating to aircraft",
        "value": "f257ae11-3be6-4d57-bfbd-299ee83d12bd"
    },
    {
        "label": "Consultancy services related to the installation of computer hardware       ",
        "value": "d2bb2c05-faf3-45dd-b735-97ef1a4e7b44"
    },
    {
        "label": "Other Human Health Services",
        "value": "254f0ca1-92c6-40b5-af47-e2be2f37d9ec"
    },
    {
        "label": "Beverages",
        "value": "80e60b8d-b762-4608-8766-cfd54d3cc282"
    },
    {
        "label": "Other",
        "value": "bf769ef4-9430-41f4-8c9b-fb015bc4a5a6"
    },
    {
        "label": "BUSINESS SERVICES",
        "value": "41c966ec-48a8-4b68-9fb4-a6ca51374c55"
    },
    {
        "label": "Crude materials, inedible, except fuels",
        "value": "ad0d6e26-d1ff-4ed8-8e76-b5d66c4a5159"
    },
    {
        "label": "Data processing services",
        "value": "f35cc60c-5d41-4c70-8751-75955c15ead2"
    },
    {
        "label": "Postal services",
        "value": "ef749564-2640-488e-8b0c-53034deb7c76"
    },
    {
        "label": "Printing, publishing",
        "value": "9f2c8cf8-b6ba-4275-9e36-4e69f5393741"
    },
    {
        "label": "Air Transport Services       ",
        "value": "586fcc1d-5abf-4379-a0c0-4290e9ab181f"
    },
    {
        "label": "Supporting services for maritime transport",
        "value": "dff81a6d-1f3e-47ad-93ca-fd2b19ac8c04"
    },
    {
        "label": "HEALTH RELATED AND SOCIAL SERVICES (other than those listed under 1.A.h-j.)",
        "value": "546c1bbd-5d05-4805-a720-ea197c91ef1a"
    },
    {
        "label": "Manufactured goods classified chiefly by material",
        "value": "5730fc7f-0387-46fc-9222-595b1ba819c2"
    },
    {
        "label": "Space Transport",
        "value": "b072b364-fc4d-4b20-b1dd-a790cf759c9b"
    },
    {
        "label": "Others",
        "value": "fd8fc93e-bee9-41ff-ad27-1412ff1b3d67"
    },
    {
        "label": "Accounting, auditing and bookeeping services     ",
        "value": "6cba3e6d-01a7-417a-b53f-3f153be8e20c"
    },
    {
        "label": "Inorganic chemicals",
        "value": "451260a2-1f64-426b-af33-edfd0f7b261b"
    },
    {
        "label": "Circuit-switched data transmission services",
        "value": "6bb33abb-910d-4207-a81f-eb947833d5c0"
    },
    {
        "label": "Sporting and other recreational services",
        "value": "cd957048-ccbc-468e-8eb9-9d97219731aa"
    },
    {
        "label": "Plastics in primary forms",
        "value": "529445ba-53e6-4faa-9f48-35618cede471"
    },
    {
        "label": "Gold, non-monetary (excluding gold ores and concentrates)",
        "value": "dadb2c8c-2d29-4d1c-8270-fa0c946721e7"
    },
    {
        "label": "Relating to other machinery and equipment",
        "value": "b180cd5d-059c-4f9b-9c53-b1a132d2669a"
    },
    {
        "label": "Miscellaneous manufactured articles, n.e.s.",
        "value": "b3984a03-fc9e-4fd3-8266-2e2f858c2726"
    },
    {
        "label": "Crude rubber (including synthetic and reclaimed)",
        "value": "a2d73f4f-b6e5-471b-9380-cc06a61ad018"
    },
    {
        "label": "Meat and meat preparations",
        "value": "8dd6213c-935a-40f5-9096-a8be77969523"
    },
    {
        "label": "Electronic mail",
        "value": "9a0b9961-168d-4562-99ef-6e2d7cbfc048"
    },
    {
        "label": "Taxation Services   ",
        "value": "989b2bc2-f808-49fa-a327-2a32c3deb7d3"
    },
    {
        "label": "Plastics in non-primary forms",
        "value": "ad6d34ce-65fb-4ec5-bdc0-268e6e5eba5f"
    },
    {
        "label": "Coin (other than gold coin), not being legal tender",
        "value": "3f738294-1e05-4ff0-99ba-7983b5b6c328"
    },
    {
        "label": "Others ",
        "value": "8f557944-d731-4cc6-aeab-c1f53f4c37cd"
    },
    {
        "label": "Other",
        "value": "6d2bd608-4cd5-4cf6-a71e-2cb5b01e4e13"
    },
    {
        "label": "Hotels and restaurants (incl. catering)",
        "value": "5eb41ee0-0a9e-4736-9179-43772f065e4c"
    },
    {
        "label": "Gas, natural and manufactured",
        "value": "3ad501a8-09b7-4977-83a0-153cbb534326"
    },
    {
        "label": "Motion picture and video tape production and distribution services",
        "value": "d2f6a2b9-1c3d-4ef7-ae2f-97bab3e068d3"
    },
    {
        "label": "Audiovisual services",
        "value": "119fe7c7-5503-4ce5-bc47-f06837182add"
    },
    {
        "label": "Advisory and other auxiliary financial services on all the activities listed in Article 1B of MTN.TNC/W/50, incl. credit reference and analysis, investment and portfolio research and advice, advice on acquisitions and on corporate restructuring and strate",
        "value": "33ce7310-5920-4f6a-adf7-541e105106b7"
    },
    {
        "label": "Crude animal and vegetable materials, n.e.s.",
        "value": "bd88986a-911c-4297-917f-1fc1f1e6fded"
    },
    {
        "label": "Convention services",
        "value": "19cef3c7-9905-4adb-b4b1-6bef35f173a6"
    },
    {
        "label": "Telegraph services",
        "value": "8ca07f21-9b45-4f1e-9f39-80b91854ce97"
    },
    {
        "label": "Electronic data interchange (EDI)",
        "value": "3b4c5ffc-9b05-48d5-a5e9-a1ae60568ce5"
    },
    {
        "label": "Services auxiliary to insurance (including broking and agency services)",
        "value": "6ff17a0f-b77c-4b55-8ba2-340f91f3b9f5"
    },
    {
        "label": "Passenger transportation",
        "value": "3e6536e4-c46d-451a-afe9-db71fc1b2d95"
    },
    {
        "label": "Freight transportation",
        "value": "9ff95d8f-9123-4bb4-ab92-666a312fc943"
    },
    {
        "label": "Servicios de almacenamiento",
        "value": "517590b7-3c6e-47ab-a482-bf23cb048ff9"
    },
    {
        "label": "R&D services on social sciences and humanities",
        "value": "4ac2d90e-dd35-4c2f-9d3e-245d8cb94976"
    },
    {
        "label": "Entertainment services (including theatre, live bands and circus services)",
        "value": "4e10ab9d-b028-41ae-83db-3c39f052937d"
    },
    {
        "label": "Oil-seeds and oleaginous fruits",
        "value": "8fbb01a4-66cf-4700-a6bd-5dafb6486ce3"
    },
    {
        "label": "Provision and transfer of financial information, and financial data processing and related software by providers of other financial services",
        "value": "4f9c87c8-cef4-4eec-8283-6ac6c88d57b8"
    },
    {
        "label": "Chemical materials and products, n.e.s.",
        "value": "9ca4db08-e2d3-4070-b09c-a2eec5ee21d4"
    },
    {
        "label": "Metalworking machinery",
        "value": "a55f1477-2799-4ae2-9271-31b4cfb4cd9e"
    },
    {
        "label": "Tourist guides services",
        "value": "ed995b3d-70d3-4c10-97c8-2ed5e0faa5da"
    },
    {
        "label": "Ohter",
        "value": "df417bb7-705a-4e78-b8af-182cd115e327"
    },
    {
        "label": "Organic chemicals",
        "value": "de67dcb2-e682-4ee0-b01b-f6bb1002b8c2"
    },
    {
        "label": "Machinery specialized for particular industries",
        "value": "1b2a04e7-d658-495e-a31f-63bf4b2ddb50"
    },
    {
        "label": "Fish (not marine mammals), crustaceans, molluscs and aquatic invertebrates, and preparations thereof",
        "value": "b2e2073b-280c-418c-b7d3-249b71d76eef"
    },
    {
        "label": "Settlement and clearing services for financial assets, incl. securities, derivative products, and other negotiable instruments",
        "value": "69d1acb7-0744-4dbd-8645-4a91b38d6df8"
    },
    {
        "label": "Entertainment services (including theatre, live bands and circus services)",
        "value": "0c22b60f-acc4-46a0-bcea-2d0517af061c"
    },
    {
        "label": "Packaging services",
        "value": "50d9fb09-a484-4e7b-96d8-6d102197d168"
    },
    {
        "label": "Trading for own account or for account of customers, whether on an exchange, in an over-the-counter market or otherwise, the following:",
        "value": "fde5d33c-8e9f-41dd-a3f1-aa3a9ef480ce"
    },
    {
        "label": "Other Transport Services ",
        "value": "1fc32646-3607-4305-b7a4-1ddcde840bdc"
    }
]
